cztile/__init__.py
cztile/fixed_total_area_strategy_2d.py
cztile/fixed_total_length_strategy_1d.py
cztile/fixed_total_volume_strategy_3d.py
cztile/tiling_strategy.py
cztile-2.0.0.dist-info/licenses/LICENSE.txt
cztile-2.0.0.dist-info/licenses/NOTICE.txt
cztile-2.0.0.dist-info/METADATA
cztile-2.0.0.dist-info/WHEEL
cztile-2.0.0.dist-info/top_level.txt
cztile-2.0.0.dist-info/RECORD
