Metadata-Version: 2.4
Name: cztile
Version: 2.0.0
Summary: A set of tiling utilities
Author-email: Sebastian Rhode <sebastian.rhode@zeiss.com>
License: 
Classifier: Development Status :: 5 - Production/Stable
Classifier: Topic :: Scientific/Engineering :: Image Processing
Classifier: Programming Language :: Python :: 3.9
Classifier: Programming Language :: Python :: 3.10
Classifier: Programming Language :: Python :: 3.11
Classifier: Programming Language :: Python :: 3.12
Classifier: Programming Language :: Python :: 3.13
Classifier: License :: OSI Approved :: Apache Software License
Classifier: Operating System :: OS Independent
Requires-Python: <3.14,>3.8
License-File: LICENSE.txt
License-File: NOTICE.txt
Dynamic: license-file
